sortingx/__init__.py
sortingx/_typing.py
sortingx/_utils.py
sortingx/sorting.py
sortingx-1.3.2.dist-info/LICENSE
sortingx-1.3.2.dist-info/METADATA
sortingx-1.3.2.dist-info/WHEEL
sortingx-1.3.2.dist-info/top_level.txt
sortingx-1.3.2.dist-info/RECORD
