Metadata-Version: 2.1
Name: sortingx
Version: 1.3.2
Summary: The powerful package designed for sorting.
Home-page: https://github.com/linjing-lab/sorting-algorithms
Download-URL: https://github.com/linjing-lab/sorting-algorithms/tags
Author: 林景
Author-email: linjing010729@163.com
License: Apache 2.0
Project-URL: Source, https://github.com/linjing-lab/sorting-algorithms/tree/main/sortingx
Project-URL: Tracker, https://github.com/linjing-lab/sorting-algorithms/issues
Classifier: Development Status :: 5 - Production/Stable
Classifier: Intended Audience :: Developers
Classifier: Intended Audience :: Education
Classifier: Intended Audience :: Science/Research
Classifier: Programming Language :: Python :: 3.7
Classifier: Programming Language :: Python :: 3.8
Classifier: Programming Language :: Python :: 3.9
Classifier: Programming Language :: Python :: 3.10
Classifier: Programming Language :: Python :: 3.11
Classifier: License :: OSI Approved :: Apache Software License
Classifier: Topic :: Software Development
Classifier: Topic :: Software Development :: Libraries
Classifier: Topic :: Software Development :: Libraries :: Python Modules
License-File: LICENSE
Requires-Dist: typing-extensions (>=3.10.0.2)
